oep_client/__init__.py
oep_client/__main__.py
oep_client/_dialect.py
oep_client/advanced_api.py
oep_client/exceptions.py
oep_client/oep_client.py
oep_client/test.py
oep_client/utils.py
oep_client-0.19.0.dist-info/licenses/LICENSE
oep_client-0.19.0.dist-info/METADATA
oep_client-0.19.0.dist-info/WHEEL
oep_client-0.19.0.dist-info/entry_points.txt
oep_client-0.19.0.dist-info/top_level.txt
oep_client-0.19.0.dist-info/RECORD
