Metadata-Version: 2.4
Name: oep-client
Version: 0.19.0
Summary: client side tool for openenergy platform
Author-email: Christian Winger <c.winger@oeko.de>
License-Expression: CC0-1.0
Project-URL: Repository, https://github.com/wingechr/oep-client
Classifier: Programming Language :: Python :: 3
Classifier: Operating System :: OS Independent
Requires-Python: >=3.10
License-File: LICENSE
Requires-Dist: click
Requires-Dist: pandas
Requires-Dist: requests
Dynamic: license-file
